authenticator/__init__.py
authenticator/authenticationbasic.py
proxyauthenticator-0.0.8.dist-info/LICENSE
proxyauthenticator-0.0.8.dist-info/METADATA
proxyauthenticator-0.0.8.dist-info/WHEEL
proxyauthenticator-0.0.8.dist-info/top_level.txt
proxyauthenticator-0.0.8.dist-info/RECORD
