Metadata-Version: 2.1
Name: proxyauthenticator
Version: 0.0.8
Summary: Proxy Authenticator for python projects
Home-page: https://github.com/NuwanChaminda/proxyauthenticator
Author: Nuwan Chaminda
Author-email: lokupodda123@gmail.com
License: UNKNOWN
Platform: UNKNOWN
Classifier: Programming Language :: Python :: 3
Classifier: License :: OSI Approved :: MIT License
Classifier: Operating System :: OS Independent
Classifier: Programming Language :: Python :: 3.7
Classifier: Programming Language :: Python :: 3.8
Requires-Python: >=3.6
License-File: LICENSE
Requires-Dist: setuptools
Requires-Dist: wheel
